<?xml version="1.0" encoding="UTF-8"?>
<tasks type="anal">
	<t><d>1</d><req>0</req>
	<me><img src="http://images.northrup.org/picture/xl/rabbit/rabbit-18.jpg" style="display: block;margin-left: auto;margin-right: auto;"></img><br/><p>Placeholder</p></me>
	</t>
	<t><d>2</d><req>0</req>
	<me><img src="http://images.northrup.org/picture/xl/rabbit/rabbit-18.jpg" style="display: block;margin-left: auto;margin-right: auto;"></img><br/><p>Placeholder</p></me>
	</t>
	<t><d>3</d><req>0</req>
	<me><img src="http://images.northrup.org/picture/xl/rabbit/rabbit-18.jpg" style="display: block;margin-left: auto;margin-right: auto;"></img><br/><p>Placeholder</p></me>
	</t>
	<t><d>4</d><req>0</req>
	<me><img src="http://images.northrup.org/picture/xl/rabbit/rabbit-18.jpg" style="display: block;margin-left: auto;margin-right: auto;"></img><br/><p>Placeholder</p></me>
	</t>
	<t><d>5</d><req>0</req>
	<me><img src="http://images.northrup.org/picture/xl/rabbit/rabbit-18.jpg" style="display: block;margin-left: auto;margin-right: auto;"></img><br/><p>Placeholder</p></me>
	</t>
	<t><d>6</d><req>0</req>
	<me><img src="http://images.northrup.org/picture/xl/rabbit/rabbit-18.jpg" style="display: block;margin-left: auto;margin-right: auto;"></img><br/><p>Placeholder</p></me>
	</t>
	<t><d>7</d><req>0</req>
	<me><img src="http://images.northrup.org/picture/xl/rabbit/rabbit-18.jpg" style="display: block;margin-left: auto;margin-right: auto;"></img><br/><p>Placeholder</p></me>
	</t>
	<t><d>8</d><req>0</req>
	<me><img src="http://images.northrup.org/picture/xl/rabbit/rabbit-18.jpg" style="display: block;margin-left: auto;margin-right: auto;"></img><br/><p>Placeholder</p></me>
	</t>
	<t><d>9</d><req>0</req>
	<me><img src="http://images.northrup.org/picture/xl/rabbit/rabbit-18.jpg" style="display: block;margin-left: auto;margin-right: auto;"></img><br/><p>Placeholder</p></me>
	</t>
</tasks>